__tests__/__init__.py
__tests__/test_case_converter.py
__tests__/test_http_event.py
__tests__/test_http_response.py
__tests__/test_jwt.py
__tests__/test_logger.py
__tests__/test_mappers.py
__tests__/test_password.py
__tests__/test_validators.py
py_aws_lambda_toolkit/__init__.py
py_aws_lambda_toolkit/case_converter.py
py_aws_lambda_toolkit/dynamodb_shortcuts.py
py_aws_lambda_toolkit/http_event.py
py_aws_lambda_toolkit/http_response.py
py_aws_lambda_toolkit/jwt.py
py_aws_lambda_toolkit/logger.py
py_aws_lambda_toolkit/mappers.py
py_aws_lambda_toolkit/password.py
py_aws_lambda_toolkit/scan_filter_builder.py
py_aws_lambda_toolkit/settings.py
py_aws_lambda_toolkit/status.py
py_aws_lambda_toolkit/validators.py
py_aws_lambda_toolkit-0.0.6.dist-info/LICENSE
py_aws_lambda_toolkit-0.0.6.dist-info/METADATA
py_aws_lambda_toolkit-0.0.6.dist-info/WHEEL
py_aws_lambda_toolkit-0.0.6.dist-info/top_level.txt
py_aws_lambda_toolkit-0.0.6.dist-info/RECORD
