Metadata-Version: 2.1
Name: py-aws-lambda-toolkit
Version: 0.0.6
Summary: A toolkit for serverless and AWS, with a focus on AWS Lambda and dynamodb.
Home-page: https://github.com/0riion/py-aws-lambda-toolkit
Author: Julio Flores
Author-email: juliocesarflores12@gmail.com
License: MIT
Keywords: aws,serverless,lambda,dynamodb,toolkit,python,aws
Classifier: Development Status :: 1 - Planning
Classifier: Intended Audience :: Developers
Classifier: License :: OSI Approved :: MIT License
Classifier: Programming Language :: Python :: 3.8
Classifier: Operating System :: OS Independent
Classifier: Topic :: Software Development :: Libraries :: Python Modules
Classifier: Topic :: Utilities
Requires-Python: >=3.8
License-File: LICENSE
Requires-Dist: boto3 (==1.26.118)
Requires-Dist: jsonschema (==4.17.3)
Requires-Dist: camel-converter (==3.0.0)
Requires-Dist: PyJWT (==2.6.0)
Requires-Dist: ruff (==0.0.277)
